scrapy_rabbitmq_scheduler/__init__.py
scrapy_rabbitmq_scheduler/connection.py
scrapy_rabbitmq_scheduler/middleware.py
scrapy_rabbitmq_scheduler/picklecompat.py
scrapy_rabbitmq_scheduler/pipelines.py
scrapy_rabbitmq_scheduler/queue.py
scrapy_rabbitmq_scheduler/scheduler.py
scrapy_rabbitmq_scheduler/spiders.py
scrapyer_rabbitmq_scheduler-1.0.7.dist-info/METADATA
scrapyer_rabbitmq_scheduler-1.0.7.dist-info/WHEEL
scrapyer_rabbitmq_scheduler-1.0.7.dist-info/top_level.txt
scrapyer_rabbitmq_scheduler-1.0.7.dist-info/RECORD
