Metadata-Version: 2.1
Name: scrapyer-rabbitmq-scheduler
Version: 1.0.7
Summary: Rabbitmq for Distributed scraping
Home-page: https://github.com/aox-lei/scrapy-rabbitmq-scheduler
Author: aox lei
Author-email: 2387813033@qq.com
License: MIT
Platform: UNKNOWN
Requires-Dist: pika
